mindmelting/__init__.py
mindmelting/powerpal/__init__.py
mindmelting/powerpal/exceptions.py
mindmelting.powerpal-0.4.0.dist-info/METADATA
mindmelting.powerpal-0.4.0.dist-info/WHEEL
mindmelting.powerpal-0.4.0.dist-info/top_level.txt
mindmelting.powerpal-0.4.0.dist-info/RECORD
