Metadata-Version: 2.1
Name: mindmelting.powerpal
Version: 0.4.0
Summary: Simple Python client for calling Powerpal Readings API.
Home-page: https://github.com/mindmelting/powerpal
Author: Lawrence Hunt
Author-email: lawrence.hunt@gmail.com
License: UNKNOWN
Platform: UNKNOWN
Requires-Python: >=3.6
Requires-Dist: aiohttp >=3.0.0
